mesh_reducer-2.0.2.dist-info/METADATA
mesh_reducer-2.0.2.dist-info/WHEEL
mesh_reducer/__init__.py
mesh_reducer/__init__.pyi
mesh_reducer/py.typed
mesh_reducer/mesh_reducer.cpython-310-x86_64-linux-gnu.so
mesh_reducer-2.0.2.dist-info/RECORD
