Metadata-Version: 2.3
Name: mesh-reducer
Version: 2.0.2
Classifier: Development Status :: 4 - Beta
Classifier: Intended Audience :: Developers
Classifier: License :: OSI Approved :: MIT License
Classifier: Programming Language :: Python
Classifier: Programming Language :: Python :: 3
Classifier: Programming Language :: Python :: 3.9
Classifier: Programming Language :: Python :: 3.10
Classifier: Programming Language :: Python :: 3.11
Classifier: Programming Language :: Python :: 3.12
Classifier: Operating System :: OS Independent
Classifier: Topic :: Software Development :: Libraries
Classifier: Topic :: Internet :: WWW/HTTP
Summary: A Python package for reading STL, OBJ files and extracting points
Keywords: stl,reducer,python,rust,pyo3,grid,voxel,mesh,obj
Author: vffuunnyy <vffuunnyy@gmail.com>
Author-email: vffuunnyy <vffuunnyy@gmail.com>
License: MIT
Requires-Python: >=3.9
Project-URL: Homepage, https://github.com/vffuunnyy/stl_reducer/
Project-URL: Documentation, https://github.com/vffuunnyy/stl_reducer/
Project-URL: Repository, https://github.com/vffuunnyy/stl_reducer.git
Project-URL: Issues, https://github.com/vffuunnyy/stl_reducer/issues
